winningvariant/__init__.py
winningvariant/_internal.py
winningvariant/assignment.py
winningvariant/client.py
winningvariant-0.1.0.dist-info/METADATA
winningvariant-0.1.0.dist-info/WHEEL
winningvariant-0.1.0.dist-info/licenses/LICENSE.txt
winningvariant-0.1.0.dist-info/RECORD
