Metadata-Version: 2.4
Name: winningvariant
Version: 0.1.0
Summary: Snowflake Native split testing client for Winning Variant
Project-URL: Homepage, https://www.winningvariant.com
Project-URL: Documentation, https://docs.winningvariant.com
Project-URL: Issues, https://github.com/winningvariant/winningvariant-python/issues
Author-email: Winning Variant <dev@winningvariant.com>
License-File: LICENSE.txt
Keywords: ab test,experimentation,snowflake experimentation,split testing,winning variant
Requires-Dist: snowflake-snowpark-python
